pyupurs/__init__.py
pyupurs/exceptions/FileIsEmptyError.py
pyupurs/exceptions/__init__.py
pyupurs/stateless_file_ops/__init__.py
pyupurs/stateless_file_ops/auditing_ops.py
pyupurs/stateless_file_ops/transversal_ops.py
tests/__init__.py
tests/pyupurs/__init__.py
tests/pyupurs/stateless_file_ops/__init__.py
tests/pyupurs/stateless_file_ops/test_auditing_ops.py
tests/pyupurs/stateless_file_ops/test_transversal_ops.py
pyupurs-0.0.6.dist-info/LICENSE.txt
pyupurs-0.0.6.dist-info/METADATA
pyupurs-0.0.6.dist-info/WHEEL
pyupurs-0.0.6.dist-info/top_level.txt
pyupurs-0.0.6.dist-info/RECORD
