Metadata-Version: 2.1
Name: pyupurs
Version: 0.0.6
Summary: PYthon Utilitary Processing, Useful and Reliable Stuff
Home-page: https://gitlab.com/ImadYIdrissi/pyupurs
Author: Imad Youbi Idrissi
Author-email: imad.youbi.idrissi@gmail.com
License: LICENSE.txt
Platform: UNKNOWN
Classifier: Programming Language :: Python :: 3.6
Classifier: Operating System :: Unix
Classifier: License :: OSI Approved :: GNU General Public License v3 (GPLv3)
Requires-Python: >=3.6
Requires-Dist: pandas
Requires-Dist: pytest
